django_routify/__init__.py
django_routify/_abstraction.py
django_routify/include.py
django_routify/patterns.py
django_routify/router.py
django_routify/validator.py
django_routify-0.3.4.dist-info/LICENSE
django_routify-0.3.4.dist-info/METADATA
django_routify-0.3.4.dist-info/WHEEL
django_routify-0.3.4.dist-info/top_level.txt
django_routify-0.3.4.dist-info/RECORD
